tomachess/__init__.py
tomachess/__main__.py
tomachess/exceptions.py
tomachess/type.py
tomachess/union_type.py
tomachess-0.1.dist-info/licenses/LICENSE
tomachess-0.1.dist-info/METADATA
tomachess-0.1.dist-info/WHEEL
tomachess-0.1.dist-info/top_level.txt
tomachess-0.1.dist-info/RECORD
