Metadata-Version: 2.4
Name: tomachess
Version: 0.1
Summary: A package to manage chess tournaments
Author-email: Moritz Eckert <MoritzEckert@web.de>
License: MIT
Project-URL: Homepage, https://github.com/Moritz72/tomachess
Classifier: Programming Language :: Python :: 3
Classifier: Operating System :: OS Independent
License-File: LICENSE
Requires-Dist: pydantic==2.11.7
Dynamic: license-file
